contributor_ci/__init__.py
contributor_ci/defaults.py
contributor_ci/logger.py
contributor_ci/version.py
contributor_ci/cfa/__init__.py
contributor_ci/cfa/cfa.yaml
contributor_ci/cfa/client.py
contributor_ci/cfa/contributor-friendliness-assessment.md
contributor_ci/cfa/template.md
contributor_ci/client/__init__.py
contributor_ci/client/cfa.py
contributor_ci/client/config.py
contributor_ci/client/extract.py
contributor_ci/client/init.py
contributor_ci/client/listing.py
contributor_ci/client/shell.py
contributor_ci/client/ui.py
contributor_ci/main/__init__.py
contributor_ci/main/client.py
contributor_ci/main/extractor.py
contributor_ci/main/schemas.py
contributor_ci/main/settings.py
contributor_ci/main/extractors/__init__.py
contributor_ci/main/extractors/activity_commits/__init__.py
contributor_ci/main/extractors/activity_commits/extract.py
contributor_ci/main/extractors/activity_lines/__init__.py
contributor_ci/main/extractors/activity_lines/extract.py
contributor_ci/main/extractors/creation_history/__init__.py
contributor_ci/main/extractors/creation_history/extract.py
contributor_ci/main/extractors/dependencies/__init__.py
contributor_ci/main/extractors/dependencies/dependencies-info.gql
contributor_ci/main/extractors/dependencies/extract.py
contributor_ci/main/extractors/languages/__init__.py
contributor_ci/main/extractors/languages/extract.py
contributor_ci/main/extractors/languages/repo-languages.gql
contributor_ci/main/extractors/member_repos/__init__.py
contributor_ci/main/extractors/member_repos/extract.py
contributor_ci/main/extractors/member_repos/user-repos.gql
contributor_ci/main/extractors/releases/__init__.py
contributor_ci/main/extractors/releases/extract.py
contributor_ci/main/extractors/releases/repo-releases.gql
contributor_ci/main/extractors/repo_dependencies/__init__.py
contributor_ci/main/extractors/repo_dependencies/extract.py
contributor_ci/main/extractors/repo_dependencies/repo-dependencies.gql
contributor_ci-0.0.17.dist-info/LICENSE
contributor_ci-0.0.17.dist-info/METADATA
contributor_ci-0.0.17.dist-info/WHEEL
contributor_ci-0.0.17.dist-info/entry_points.txt
contributor_ci-0.0.17.dist-info/top_level.txt
contributor_ci-0.0.17.dist-info/RECORD
