Metadata-Version: 2.1
Name: contributor-ci
Version: 0.0.17
Summary: automated tools to assess contributions.
Home-page: https://github.com/vsoch/contributor-ci
Author: Vanessa Sochat
Author-email: vsoch@users.noreply.github.com
Maintainer: Vanessa Sochat
License: LICENSE
Keywords: contributions,contributors,GitHub action,automated
Classifier: Intended Audience :: Science/Research
Classifier: Intended Audience :: Developers
Classifier: License :: OSI Approved :: Mozilla Public License 2.0 (MPL 2.0)
Classifier: Programming Language :: C
Classifier: Programming Language :: Python
Classifier: Topic :: Software Development
Classifier: Topic :: Scientific/Engineering
Classifier: Operating System :: Unix
Classifier: Programming Language :: Python :: 3.3
License-File: LICENSE
Requires-Dist: Jinja2
Requires-Dist: jsonschema
Requires-Dist: ruamel.yaml
Requires-Dist: llnl-scraper (>=0.10.0)
Provides-Extra: all
Requires-Dist: Jinja2 ; extra == 'all'
Requires-Dist: jsonschema ; extra == 'all'
Requires-Dist: ruamel.yaml ; extra == 'all'
Requires-Dist: llnl-scraper (>=0.10.0) ; extra == 'all'
Requires-Dist: pytest (>=4.6.2) ; extra == 'all'
